hellobc/__init__.py
hellobc/test_pip.py
hellobc/demulti/__init__.py
hellobc/demulti/parsebc.py
hellobc/demulti/samplefiles.py
hellobc/fileprocess/__init__.py
hellobc/fileprocess/fastq_process.py
hellobc/fileprocess/sam_process.py
hellobc/getcount/__init__.py
hellobc/getcount/bcgenecount.py
hellobc/getcount/bcrkplt.py
hellobc/getcount/dropcalling.py
hellobc/pipline/__init__.py
hellobc/pipline/runpip.py
hellobc/utils/__init__.py
hellobc/utils/fileop.py
hellobc/utils/sysop.py
hellobc-0.1.0.dist-info/LICENSE
hellobc-0.1.0.dist-info/METADATA
hellobc-0.1.0.dist-info/WHEEL
hellobc-0.1.0.dist-info/top_level.txt
hellobc-0.1.0.dist-info/RECORD
