Metadata-Version: 2.1
Name: hellobc
Version: 0.1.0
Summary: XuLab package for single-cell RNA-seq data upstream processing.
Requires-Python: >=3.6
License-File: LICENSE
Requires-Dist: biopython >=1.80
Requires-Dist: pysam >=0.18.0
Requires-Dist: pandas >=1.5.0
Requires-Dist: numpy >=1.22.0
Requires-Dist: matplotlib >=3.4.0
Requires-Dist: scipy >=1.8.0
Requires-Dist: pyranges >=0.0.85
